AUTHORS.rst
LICENSE.rst
MANIFEST.in
README.rst
setup.cfg
setup.py
django_shop_credomatic.egg-info/PKG-INFO
django_shop_credomatic.egg-info/SOURCES.txt
django_shop_credomatic.egg-info/dependency_links.txt
django_shop_credomatic.egg-info/not-zip-safe
django_shop_credomatic.egg-info/requires.txt
django_shop_credomatic.egg-info/top_level.txt
shop_bac/__init__.py
shop_bac/bac.py
shop_bac/forms.py
shop_bac/models.py
shop_bac/templates/shop_bac/confirm_payment.html
shop_bac/templates/shop_bac/payment.html
shop_bac/templates/shop_bac/success.html