Metadata-Version: 1.0
Name: django-shop-credomatic
Version: 0.0.1
Summary: Credomatic payment backend
Home-page: UNKNOWN
Author: Laoska Guadamuz
Author-email: lbgm2011@gmail.com
License: UNKNOWN
Platform: OS Independent
